Workbook

Sheet Graficas
B2: Bonanza
B3: ESTATUS UNIDADES PARA ENTREGA
G5: ENTREGADAS A PVTA | J5: 20.33
C6: UNIDADES | D6: VTAS USD | E6: COB USD | F6: X COB USD | G6: RECIBIDO | H6: ENTREGADO | I6: X COB REC USD | J6: VAL LIB USD | K6: DIF
B7: SOLD | C7: =COUNTIF(Bonanza!$O$7:$O$197,Graficas!$B7) -> 184 | D7: =SUMIFS(Bonanza!$P:$P,Bonanza!$O:$O,Graficas!$B7) -> 37005200 | E7: =SUMIFS(Bonanza!$R:$R,Bonanza!$O:$O,Graficas!$B7) -> 16304488 | F7: =D7-E7 -> 20700712 | G7: =COUNTIFS(Bonanza!$AE:$AE,Graficas!G$6,Bonanza!$O:$O,Graficas!$B7) -> 0 | H7: =COUNTIFS(Bonanza!$AE:$AE,Graficas!H$6,Bonanza!$O:$O,Graficas!$B7) -> 0 | I7: =SUMIFS(Bonanza!$T:$T,Bonanza!$O:$O,Graficas!$B7,Bonanza!$AE:$AE,Graficas!$G6) -> 0 | J7: =SUMIFS(Bonanza!$X:$X,Bonanza!$O:$O,Graficas!$B7,Bonanza!$AE:$AE,Graficas!$G$6)/20.33 -> 0 | K7: =I7-J7 -> 0
B8: AVAILABLE | C8: =COUNTIF(Bonanza!$O$7:$O$197,Graficas!$B8) -> 7 | D8: =SUMIFS(Bonanza!$P:$P,Bonanza!$O:$O,Graficas!$B8) -> 0 | E8: =SUMIFS(Bonanza!$R:$R,Bonanza!$O:$O,Graficas!$B8) -> 0 | F8: =D8-E8 -> 0 | G8: =COUNTIFS(Bonanza!$AE:$AE,Graficas!G$6,Bonanza!$O:$O,Graficas!$B8) -> 0 | H8: =COUNTIFS(Bonanza!$AE:$AE,Graficas!H$6,Bonanza!$O:$O,Graficas!$B8) -> 0 | I8: =SUMIFS(Bonanza!$T:$T,Bonanza!$O:$O,Graficas!$B8,Bonanza!$AE:$AE,Graficas!$G6) -> 0 | J8: =SUMIFS(Bonanza!$X:$X,Bonanza!$O:$O,Graficas!$B8,Bonanza!$AE:$AE,Graficas!$G$6)/20.33 -> 0 | K8: =I8-J8 -> 0
B10: TOTALES | C10: =SUM(C7:C9) -> 191 | D10: =SUM(D7:D9) -> 37005200 | E10: =SUM(E7:E9) -> 16304488 | F10: =SUM(F7:F9) -> 20700712 | G10: =SUM(G7:G9) -> 0 | H10: =SUM(H7:H9) -> 0 | I10: =SUM(I7:I9) -> 0 | J10: =SUM(J7:J9) -> 0 | K10: =SUM(K7:K9) -> 0

Sheet RESUMEN
K1: 18.5
B4: USD | C4: UNIDS | D4: RETA OP FIN | E4: RETA | F4: GENERAL | H4: MXN | J4: RETA OP FIN | K4: RETA | L4: GENERAL | N4: BONANZA | P4: RETA OP FIN | Q4: RETA | R4: GENERAL
B5: SOLD | C5: =COUNTIFS(Bonanza!$O:$O,RESUMEN!$B5,Bonanza!$D:$D,RESUMEN!$B$4) -> 123 | D5: =COUNTIFS(Bonanza!$O:$O,RESUMEN!$B5,Bonanza!$D:$D,RESUMEN!$B$4,Bonanza!$M:$M,RESUMEN!D$4) -> 98 | E5: =COUNTIFS(Bonanza!$O:$O,RESUMEN!$B5,Bonanza!$D:$D,RESUMEN!$B$4,Bonanza!$M:$M,RESUMEN!E$4) -> 25 | F5: =COUNTIFS(Bonanza!$O:$O,RESUMEN!$B5,Bonanza!$D:$D,RESUMEN!$B$4,Bonanza!$M:$M,RESUMEN!F$4) -> 0 | H5: SOLD | I5: =COUNTIFS(Bonanza!$O:$O,RESUMEN!$H5,Bonanza!$D:$D,RESUMEN!$H$4) -> 61 | J5: =COUNTIFS(Bonanza!$O:$O,RESUMEN!$H5,Bonanza!$D:$D,RESUMEN!$H$4,Bonanza!$M:$M,RESUMEN!D$4) -> 0 | K5: =COUNTIFS(Bonanza!$O:$O,RESUMEN!$H5,Bonanza!$D:$D,RESUMEN!$H$4,Bonanza!$M:$M,RESUMEN!E$4) -> 0 | L5: =COUNTIFS(Bonanza!$O:$O,RESUMEN!$H5,Bonanza!$D:$D,RESUMEN!$H$4,Bonanza!$M:$M,RESUMEN!F$4) -> 61 | N5: SOLD | O5: =C5+I5 -> 184 | P5: =D5+J5 -> 98 | Q5: =E5+K5 -> 25 | R5: =F5+L5 -> 61
B6: AVAILABLE | C6: =COUNTIFS(Bonanza!$O:$O,RESUMEN!$B6,Bonanza!$D:$D,RESUMEN!$B$4) -> 0 | D6: =COUNTIFS(Bonanza!$O:$O,RESUMEN!$B6,Bonanza!$D:$D,RESUMEN!$B$4,Bonanza!$M:$M,RESUMEN!D$4) -> 0 | E6: =COUNTIFS(Bonanza!$O:$O,RESUMEN!$B6,Bonanza!$D:$D,RESUMEN!$B$4,Bonanza!$M:$M,RESUMEN!E$4) -> 0 | F6: =COUNTIFS(Bonanza!$O:$O,RESUMEN!$B6,Bonanza!$D:$D,RESUMEN!$B$4,Bonanza!$M:$M,RESUMEN!F$4) -> 0 | H6: AVAILABLE | I6: =COUNTIFS(Bonanza!$O:$O,RESUMEN!$H6,Bonanza!$D:$D,RESUMEN!$H$4) -> 7 | J6: =COUNTIFS(Bonanza!$O:$O,RESUMEN!$H6,Bonanza!$D:$D,RESUMEN!$H$4,Bonanza!$M:$M,RESUMEN!D$4) -> 0 | K6: =COUNTIFS(Bonanza!$O:$O,RESUMEN!$H6,Bonanza!$D:$D,RESUMEN!$H$4,Bonanza!$M:$M,RESUMEN!E$4) -> 0 | L6: =COUNTIFS(Bonanza!$O:$O,RESUMEN!$H6,Bonanza!$D:$D,RESUMEN!$H$4,Bonanza!$M:$M,RESUMEN!F$4) -> 7 | N6: AVAILABLE | O6: =C6+I6 -> 7 | P6: =D6+J6 -> 0 | Q6: =E6+K6 -> 0 | R6: =F6+L6 -> 7
B7: DESACTIVADO | C7: =COUNTIFS(Bonanza!$O:$O,RESUMEN!$B7,Bonanza!$D:$D,RESUMEN!$B$4) -> 0 | D7: =COUNTIFS(Bonanza!$O:$O,RESUMEN!$B7,Bonanza!$D:$D,RESUMEN!$B$4,Bonanza!$M:$M,RESUMEN!D$4) -> 0 | E7: =COUNTIFS(Bonanza!$O:$O,RESUMEN!$B7,Bonanza!$D:$D,RESUMEN!$B$4,Bonanza!$M:$M,RESUMEN!E$4) -> 0 | F7: =COUNTIFS(Bonanza!$O:$O,RESUMEN!$B7,Bonanza!$D:$D,RESUMEN!$B$4,Bonanza!$M:$M,RESUMEN!F$4) -> 0 | H7: DESACTIVADO | I7: =COUNTIFS(Bonanza!$O:$O,RESUMEN!$H7,Bonanza!$D:$D,RESUMEN!$H$4) -> 0 | J7: =COUNTIFS(Bonanza!$O:$O,RESUMEN!$H7,Bonanza!$D:$D,RESUMEN!$H$4,Bonanza!$M:$M,RESUMEN!D$4) -> 0 | K7: =COUNTIFS(Bonanza!$O:$O,RESUMEN!$H7,Bonanza!$D:$D,RESUMEN!$H$4,Bonanza!$M:$M,RESUMEN!E$4) -> 0 | L7: =COUNTIFS(Bonanza!$O:$O,RESUMEN!$H7,Bonanza!$D:$D,RESUMEN!$H$4,Bonanza!$M:$M,RESUMEN!F$4) -> 0 | N7: DESACTIVADO | O7: =C7+I7 -> 0 | P7: =D7+J7 -> 0 | Q7: =E7+K7 -> 0 | R7: =F7+L7 -> 0
C8: =COUNTIFS(Bonanza!$O:$O,RESUMEN!$B8,Bonanza!$D:$D,RESUMEN!$B$4) -> 0 | D8: =COUNTIFS(Bonanza!$O:$O,RESUMEN!$B8,Bonanza!$D:$D,RESUMEN!$B$4,Bonanza!$M:$M,RESUMEN!D$4) -> 0 | E8: =COUNTIFS(Bonanza!$O:$O,RESUMEN!$B8,Bonanza!$D:$D,RESUMEN!$B$4,Bonanza!$M:$M,RESUMEN!E$4) -> 0 | F8: =COUNTIFS(Bonanza!$O:$O,RESUMEN!$B8,Bonanza!$D:$D,RESUMEN!$B$4,Bonanza!$M:$M,RESUMEN!F$4) -> 0 | I8: =COUNTIFS(Bonanza!$O:$O,RESUMEN!$H8,Bonanza!$D:$D,RESUMEN!$H$4) -> 0 | J8: =COUNTIFS(Bonanza!$O:$O,RESUMEN!$H8,Bonanza!$D:$D,RESUMEN!$H$4,Bonanza!$M:$M,RESUMEN!D$4) -> 0 | K8: =COUNTIFS(Bonanza!$O:$O,RESUMEN!$H8,Bonanza!$D:$D,RESUMEN!$H$4,Bonanza!$M:$M,RESUMEN!E$4) -> 0 | L8: =COUNTIFS(Bonanza!$O:$O,RESUMEN!$H8,Bonanza!$D:$D,RESUMEN!$H$4,Bonanza!$M:$M,RESUMEN!F$4) -> 0 | O8: =C8+I8 -> 0 | P8: =D8+J8 -> 0 | Q8: =E8+K8 -> 0 | R8: =F8+L8 -> 0
B9: TOTAL | C9: =SUM(C5:C8) -> 123 | D9: =SUM(D5:D8) -> 98 | E9: =SUM(E5:E8) -> 25 | F9: =SUM(F5:F8) -> 0 | H9: TOTAL | I9: =SUM(I5:I8) -> 68 | J9: =SUM(J5:J8) -> 0 | K9: =SUM(K5:K8) -> 0 | L9: =SUM(L5:L8) -> 68 | N9: TOTAL | O9: =SUM(O5:O8) -> 191 | P9: =SUM(P5:P8) -> 98 | Q9: =SUM(Q5:Q8) -> 25 | R9: =SUM(R5:R8) -> 68
B12: USD | C12: VENTAS | D12: COBRADO | E12: X COBRAR | F12: X FINANCIAR | G12: X COBRAR RECURSO PROPIO
B13: RETA OP FIN | C13: =SUMIF(Bonanza!$M:$M,RESUMEN!$B13,Bonanza!$P:$P) -> 29786800 | D13: =SUMIF(Bonanza!$M:$M,RESUMEN!$B13,Bonanza!$R:$R) -> 13198699 | E13: =SUMIF(Bonanza!$M:$M,RESUMEN!$B13,Bonanza!$T:$T) -> 16588101 | F13: =SUMIF(Bonanza!$M:$M,RESUMEN!$B13,Bonanza!#REF!) -> #REF! | G13: =E13-F13 -> #REF!
B14: RETA | C14: =SUMIF(Bonanza!$M:$M,RESUMEN!$B14,Bonanza!$P:$P) -> 7218400 | D14: =SUMIF(Bonanza!$M:$M,RESUMEN!$B14,Bonanza!$R:$R) -> 3105789 | E14: =SUMIF(Bonanza!$M:$M,RESUMEN!$B14,Bonanza!$T:$T) -> 4112611 | F14: =SUMIF(Bonanza!$M:$M,RESUMEN!$B14,Bonanza!#REF!) -> #REF! | G14: =E14-F14 -> #REF!
B15: GENERAL | C15: =SUMIF(Bonanza!$M:$M,RESUMEN!$B15,Bonanza!$P:$P) -> 0 | D15: =SUMIF(Bonanza!$M:$M,RESUMEN!$B15,Bonanza!$R:$R) -> 0 | E15: =SUMIF(Bonanza!$M:$M,RESUMEN!$B15,Bonanza!$T:$T) -> 0 | F15: =SUMIF(Bonanza!$M:$M,RESUMEN!$B15,Bonanza!#REF!) -> #REF! | G15: =E15-F15 -> #REF!
C16: =SUMIF(Bonanza!$M:$M,RESUMEN!$B16,Bonanza!$P:$P) -> 0 | D16: =SUMIF(Bonanza!$M:$M,RESUMEN!$B16,Bonanza!$R:$R) -> 0 | E16: =SUMIF(Bonanza!$M:$M,RESUMEN!$B16,Bonanza!$T:$T) -> 0 | F16: =SUMIF(Bonanza!$M:$M,RESUMEN!$B16,Bonanza!#REF!) -> #REF! | G16: =E16-F16 -> #REF!
B17: TOTAL | C17: =SUM(C13:C16) -> 37005200 | D17: =SUM(D13:D16) -> 16304488 | E17: =SUM(E13:E16) -> 20700712 | F17: =SUM(F13:F16) -> #REF! | G17: =SUM(G13:G16) -> #REF!
B19: MXN | C19: VENTAS | D19: COBRADO | E19: X COBRAR | F19: X FINANCIAR | G19: X COBRAR RECURSO PROPIO
B20: RETA OP FIN | C20: =SUMIFS(Bonanza!$Q:$Q,Bonanza!$M:$M,RESUMEN!$B20,Bonanza!$D:$D,RESUMEN!$B$19) -> 0 | D20: =SUMIFS(Bonanza!$S:$S,Bonanza!$M:$M,RESUMEN!$B20,Bonanza!$D:$D,RESUMEN!$B$19) -> 0 | E20: =SUMIFS(Bonanza!$U:$U,Bonanza!$M:$M,RESUMEN!$B20,Bonanza!$D:$D,RESUMEN!$B$19) -> 0 | F20: =SUMIFS(Bonanza!#REF!,Bonanza!$M:$M,RESUMEN!$B20,Bonanza!$D:$D,RESUMEN!$B$19) -> #REF! | G20: =E20-F20 -> #REF!
B21: RETA | C21: =SUMIFS(Bonanza!$Q:$Q,Bonanza!$M:$M,RESUMEN!$B21,Bonanza!$D:$D,RESUMEN!$B$19) -> 0 | D21: =SUMIFS(Bonanza!$S:$S,Bonanza!$M:$M,RESUMEN!$B21,Bonanza!$D:$D,RESUMEN!$B$19) -> 0 | E21: =SUMIFS(Bonanza!$U:$U,Bonanza!$M:$M,RESUMEN!$B21,Bonanza!$D:$D,RESUMEN!$B$19) -> 0 | F21: =SUMIFS(Bonanza!#REF!,Bonanza!$M:$M,RESUMEN!$B21,Bonanza!$D:$D,RESUMEN!$B$19) -> #REF! | G21: =E21-F21 -> #REF!
B22: GENERAL | C22: =SUMIFS(Bonanza!$Q:$Q,Bonanza!$M:$M,RESUMEN!$B22,Bonanza!$D:$D,RESUMEN!$B$19) -> 5.6820131e+08 | D22: =SUMIFS(Bonanza!$S:$S,Bonanza!$M:$M,RESUMEN!$B22,Bonanza!$D:$D,RESUMEN!$B$19) -> 2.9718172e+08 | E22: =SUMIFS(Bonanza!$U:$U,Bonanza!$M:$M,RESUMEN!$B22,Bonanza!$D:$D,RESUMEN!$B$19) -> 2.7101958e+08 | F22: =SUMIFS(Bonanza!#REF!,Bonanza!$M:$M,RESUMEN!$B22,Bonanza!$D:$D,RESUMEN!$B$19) -> #REF! | G22: =E22-F22 -> #REF!
C23: =SUMIF(Bonanza!$M:$M,RESUMEN!$B23,Bonanza!$Q:$Q) -> 0 | D23: =SUMIFS(Bonanza!$S:$S,Bonanza!$M:$M,RESUMEN!$B23,Bonanza!$D:$D,RESUMEN!$B$19) -> 0 | E23: =SUMIFS(Bonanza!$U:$U,Bonanza!$M:$M,RESUMEN!$B23,Bonanza!$D:$D,RESUMEN!$B$19) -> 0 | F23: =SUMIFS(Bonanza!#REF!,Bonanza!$M:$M,RESUMEN!$B23,Bonanza!$D:$D,RESUMEN!$B$19) -> #REF! | G23: =E23-F23 -> #REF!
B24: TOTAL | C24: =SUM(C20:C23) -> 5.6820131e+08 | D24: =SUM(D20:D23) -> 2.9718172e+08 | E24: =SUM(E20:E23) -> 2.7101958e+08 | F24: =SUM(F20:F23) -> #REF! | G24: =SUM(G20:G23) -> #REF!
B26: BONANZA MXN | C26: VENTAS | D26: COBRADO | E26: X COBRAR | F26: X FINANCIAR | G26: X COBRAR RECURSO PROPIO
B27: RETA OP FIN | C27: =SUM((C13*$K$1)+C20) -> 551055800 | D27: =SUM((D13*$K$1)+D20) -> 2.4417593e+08 | E27: =SUM((E13*$K$1)+E20) -> 3.0687987e+08 | F27: =SUM((F13*$K$1)+F20) -> #REF! | G27: =SUM((G13*$K$1)+G20) -> #REF!
B28: RETA | C28: =SUM((C14*$K$1)+C21) -> 133540400 | D28: =SUM((D14*$K$1)+D21) -> 57457096 | E28: =SUM((E14*$K$1)+E21) -> 76083304 | F28: =SUM((F14*$K$1)+F21) -> #REF! | G28: =SUM((G14*$K$1)+G21) -> #REF!
B29: GENERAL | C29: =SUM((C15*$K$1)+C22) -> 5.6820131e+08 | D29: =SUM((D15*$K$1)+D22) -> 2.9718172e+08 | E29: =SUM((E15*$K$1)+E22) -> 2.7101958e+08 | F29: =SUM((F15*$K$1)+F22) -> #REF! | G29: =SUM((G15*$K$1)+G22) -> #REF!
C30: =SUM((C16*$K$1)+C23) -> 0 | D30: =SUM((D16*$K$1)+D23) -> 0 | E30: =SUM((E16*$K$1)+E23) -> 0 | F30: =SUM((F16*$K$1)+F23) -> #REF! | G30: =SUM((G16*$K$1)+G23) -> #REF!
B31: TOTAL | C31: =SUM(C27:C30) -> 1.2527975e+09 | D31: =SUM(D27:D30) -> 5.9881475e+08 | E31: =SUM(E27:E30) -> 6.5398276e+08 | F31: =SUM(F27:F30) -> #REF! | G31: =SUM(G27:G30) -> #REF!

Sheet Bonanza
B2: Relación de Departamentos para entrega | Z2: SUPERAVIT/DEFICIT
U3: 18.5 | W3: CREDITO | Y3: =X3-Y4 -> 0 | Z3: =U4-Y3 -> 6.5398276e+08
C4: =SUBTOTAL(3,C7:C197) -> 191 | M4: =SUBTOTAL(3,M7:M197) -> 191 | P4: =SUBTOTAL(9,P7:P197) -> 37005200 | Q4: =SUBTOTAL(9,Q7:Q197) -> 1.2527975e+09 | R4: =SUBTOTAL(9,R7:R197) -> 16304488 | S4: =SUBTOTAL(9,S7:S197) -> 2.9718172e+08 | T4: =SUBTOTAL(9,T7:T197) -> 20700712 | U4: =SUBTOTAL(9,U7:U197) -> 6.5398276e+08 | W4: =SUBTOTAL(3,$W$7:$W$197) -> 98 | X4: =SUBTOTAL(9,X7:X197) -> #N/A | Y4: =SUM(Y7:Y197) -> 0 | Z4: =SUBTOTAL(9,Z7:Z197) -> #N/A | AE4: =SUBTOTAL(3,AE7:AE197) -> 0
B5: VENTAS | X5: BANCO | AB5: LEGAL | AE5: POSTVENTA
B6: No. | C6: unit_id | D6: MONEDA | E6: TYPE | F6: NOMBRE (S) | G6: APELLIDO 1 | H6: APELLIDO 2 | I6: ALIAS / RAZON SOCIAL | J6: @mail | K6: LADA | L6: Telefono | M6: TIPO CLIENTE | N6: TIPO CONTRATO | O6: STATUS SISTEMA | P6: MONTO DE VENTA USD | Q6: MONTO DE VENTA MN | R6: PAGADO USD | S6: PAGADO MN | T6: SALDO USD | U6: SALDO MN | V6: FECHA COBRO SALDO | W6: FORMA PAGO | X6: VALOR LIBERACION | Y6: PAGADO LIBERACION | Z6: X PAGAR | AA6: FECHA LIBERACIÓN | AB6: ESCRITURACION | AC6: FECHA ESCRITURACION | AD6: NOTARIA | AE6: STATUS SOS | AF6: FECHA SEGÚN CONTRATO | AG6: ÚLTIMO CONTACTO SOS | AI6: FECHA ENTREGA OBRA | AJ6: estatus_obra | AK6: FECHA ENTREGA CLIENTE | AL6: COMENTARIOS | AM6: TICKET | AO6: Departamento | AP6: Fecha de Control calidad | AQ6: Fecha posible de entrega final | AR6: Tipo de dueño | AS6: Estatus
B7: 1 | C7: 1 | D7: USD | F7: CHRISTOPHER MICHAEL | G7: DAVIS | M7: RETA | O7: SOLD | P7: 375000 | Q7: =P7*$U$3 -> 6937500 | R7: 374500 | T7: =P7-R7 -> 500 | U7: =T7*U$3 -> 9250 | X7: =VLOOKUP(C7,Banorte!F:K,6,FALSE) -> #N/A | Z7: =X7-Y7 -> #N/A | AI7: 46265 | AO7: V01 | AP7: 46227 | AQ7: 46265 | AR7: RETA | AS7: PAGADO
B8: 124 | C8: 2 | D8: MXN | F8: CLAUDIA | G8: RASCON | H8: BUSTILLOS | M8: GENERAL | O8: SOLD | Q8: 10990000 | S8: 3297132.1 | U8: =Q8-S8 -> 7692867.8 | X8: =VLOOKUP(C8,Banorte!F:K,6,FALSE) -> #N/A | Z8: =X8-Y8 -> #N/A | AI8: 46265 | AO8: V02 | AP8: 46227 | AQ8: 46265 | AR8: GENERAL
B9: 125 | C9: 3 | D9: MXN | F9: SERGIO | G9: RASCON | H9: BUSTILLOS | M9: GENERAL | O9: SOLD | Q9: 13720000 | S9: 13720000 | U9: =Q9-S9 -> 0 | X9: =VLOOKUP(C9,Banorte!F:K,6,FALSE) -> #N/A | Z9: =X9-Y9 -> #N/A | AI9: 46265 | AO9: V03 | AP9: 46227 | AQ9: 46265 | AR9: GENERAL | AS9: PAGADO
B10: 2 | C10: 4 | D10: USD | F10: JOHN MARK | G10: JONES | M10: RETA OP FIN | O10: SOLD | P10: 375000 | Q10: =P10*$U$3 -> 6937500 | R10: 133220 | T10: =P10-R10 -> 241780 | U10: =T10*U$3 -> 4472930 | W10: CREDITO RETA | X10: =VLOOKUP(C10,Banorte!F:K,6,FALSE) -> #N/A | Z10: =X10-Y10 -> #N/A | AI10: 46265 | AO10: V04 | AP10: 46227 | AQ10: 46265 | AR10: RETA OP FIN
B11: 3 | C11: 5 | D11: USD | F11: ROBERT NEAL | G11: WILLIAMS JR | M11: RETA | O11: SOLD | P11: 375000 | Q11: =P11*$U$3 -> 6937500 | R11: 135800 | T11: =P11-R11 -> 239200 | U11: =T11*U$3 -> 4425200 | X11: =VLOOKUP(C11,Banorte!F:K,6,FALSE) -> #N/A | Z11: =X11-Y11 -> #N/A | AI11: 46265 | AO11: V05 | AP11: 46227 | AQ11: 46265 | AR11: RETA
B12: 4 | C12: 6 | D12: USD | F12: JASON | G12: TODT | M12: RETA OP FIN | O12: SOLD | P12: 375000 | Q12: =P12*$U$3 -> 6937500 | R12: 133220 | T12: =P12-R12 -> 241780 | U12: =T12*U$3 -> 4472930 | W12: CREDITO RETA | X12: =VLOOKUP(C12,Banorte!F:K,6,FALSE) -> #N/A | Z12: =X12-Y12 -> #N/A | AI12: 46265 | AO12: V06 | AP12: 46227 | AQ12: 46265 | AR12: RETA OP FIN
B13: 5 | C13: 7 | D13: USD | F13: ROBERT ANTHONY | G13: PALMA | M13: RETA OP FIN | O13: SOLD | P13: 375000 | Q13: =P13*$U$3 -> 6937500 | R13: 133220 | T13: =P13-R13 -> 241780 | U13: =T13*U$3 -> 4472930 | W13: CREDITO RETA | X13: =VLOOKUP(C13,Banorte!F:K,6,FALSE) -> #N/A | Z13: =X13-Y13 -> #N/A | AI13: 46265 | AO13: V07 | AP13: 46227 | AQ13: 46265 | AR13: RETA OP FIN
B14: 6 | C14: 8 | D14: USD | F14: MCGREGOR | G14: MARGARET | M14: RETA OP FIN | O14: SOLD | P14: 375000 | Q14: =P14*$U$3 -> 6937500 | R14: 207852.45 | T14: =P14-R14 -> 167147.55 | U14: =T14*U$3 -> 3092229.7 | W14: CREDITO RETA | X14: =VLOOKUP(C14,Banorte!F:K,6,FALSE) -> #N/A | Z14: =X14-Y14 -> #N/A | AI14: 46265 | AO14: V08 | AP14: 46227 | AQ14: 46265 | AR14: RETA OP FIN
B15: 7 | C15: 9 | D15: USD | F15: ROBERT MILES | G15: GILLESPIE | M15: RETA OP FIN | O15: SOLD | P15: 375000 | Q15: =P15*$U$3 -> 6937500 | R15: 133220 | T15: =P15-R15 -> 241780 | U15: =T15*U$3 -> 4472930 | W15: CREDITO RETA | X15: =VLOOKUP(C15,Banorte!F:K,6,FALSE) -> #N/A | Z15: =X15-Y15 -> #N/A | AI15: 46265 | AO15: V09 | AP15: 46227 | AQ15: 46265 | AR15: RETA OP FIN
B16: 126 | C16: 10 | D16: MXN | F16: MANUEL ENRIQUE | G16: GARCIA | H16: GARZA | M16: GENERAL | O16: SOLD | Q16: 13426000 | S16: 3356500 | U16: =Q16-S16 -> 10069500 | X16: =VLOOKUP(C16,Banorte!F:K,6,FALSE) -> #N/A | Z16: =X16-Y16 -> #N/A | AI16: 46265 | AO16: V10 | AP16: 46227 | AQ16: 46265 | AR16: GENERAL
B17: 135 | C17: 11 | D17: MXN | F17: eduardo | G17: BARAJAS | H17: SANCHEZ | M17: GENERAL | O17: SOLD | Q17: 8504475 | S17: 7223803.8 | U17: =Q17-S17 -> 1280671.2 | X17: =VLOOKUP(C17,Banorte!F:K,6,FALSE) -> #N/A | Z17: =X17-Y17 -> #N/A | AI17: 46265 | AO17: V11 | AP17: 46227 | AQ17: 46265 | AR17: GENERAL
B18: 153 | C18: 12 | D18: MXN | F18: JESÃšS RODRIGO | G18: MATA | H18: PAREDES | M18: GENERAL | O18: SOLD | Q18: 8767500 | S18: 2470399 | U18: =Q18-S18 -> 6297101 | X18: =VLOOKUP(C18,Banorte!F:K,6,FALSE) -> #N/A | Z18: =X18-Y18 -> #N/A | AI18: 46265 | AO18: V12 | AP18: 46227 | AQ18: 46265 | AR18: GENERAL
B19: 8 | C19: 13 | D19: USD | F19: CYNTHIA MARY | G19: DICKINS COLLIN SMITH | M19: RETA OP FIN | O19: SOLD | P19: 325000 | Q19: =P19*$U$3 -> 6012500 | R19: 123220 | T19: =P19-R19 -> 201780 | U19: =T19*U$3 -> 3732930 | W19: CREDITO RETA | X19: =VLOOKUP(C19,Banorte!F:K,6,FALSE) -> #N/A | Z19: =X19-Y19 -> #N/A | AI19: 46265 | AO19: V13 | AP19: 46227 | AQ19: 46265 | AR19: RETA OP FIN
B20: 159 | C20: 14 | D20: MXN | F20: FRANCISCO JAVIER | G20: VARGAS | H20: DEL TORO | M20: GENERAL | O20: SOLD | Q20: 8882500 | S20: 2664750 | U20: =Q20-S20 -> 6217750 | X20: =VLOOKUP(C20,Banorte!F:K,6,FALSE) -> #N/A | Z20: =X20-Y20 -> #N/A | AI20: 46265 | AO20: V14 | AP20: 46227 | AQ20: 46265 | AR20: GENERAL
B21: 160 | C21: 15 | D21: MXN | F21: COLIN robert | G21: CARRIE | M21: GENERAL | O21: SOLD | Q21: 8438375 | S21: 6750700 | U21: =Q21-S21 -> 1687675 | X21: =VLOOKUP(C21,Banorte!F:K,6,FALSE) -> #N/A | Z21: =X21-Y21 -> #N/A | AI21: 46265 | AO21: V15 | AP21: 46227 | AQ21: 46265 | AR21: GENERAL
B22: 161 | C22: 16 | D22: MXN | F22: HABSY MARIA | G22: AGUIRRE | H22: KURI | M22: GENERAL | O22: SOLD | Q22: 6381375 | S22: 1915343.8 | U22: =Q22-S22 -> 4466031.2 | X22: =VLOOKUP(C22,Banorte!F:K,6,FALSE) -> #N/A | Z22: =X22-Y22 -> #N/A | AI22: 46265 | AO22: V16 | AP22: 46227 | AQ22: 46265 | AR22: GENERAL
B23: 162 | C23: 17 | D23: MXN | F23: EFRÃ‰N ALBERTO | G23: SÃNCHEZ | H23: CAMPOS | M23: GENERAL | O23: SOLD | Q23: 9621150 | S23: 5500000 | U23: =Q23-S23 -> 4121150 | X23: =VLOOKUP(C23,Banorte!F:K,6,FALSE) -> #N/A | Z23: =X23-Y23 -> #N/A | AI23: 46265 | AO23: V17 | AP23: 46227 | AQ23: 46265 | AR23: GENERAL
B24: 163 | C24: 18 | D24: MXN | F24: GIMER AUGURIO | G24: PIÃ‘A | H24: HERRERA | M24: GENERAL | O24: SOLD | Q24: 9817500 | S24: 4432738 | U24: =Q24-S24 -> 5384762 | X24: =VLOOKUP(C24,Banorte!F:K,6,FALSE) -> #N/A | Z24: =X24-Y24 -> #N/A | AI24: 46265 | AO24: V18 | AP24: 46227 | AQ24: 46265 | AR24: GENERAL
B25: 9 | C25: 19 | D25: USD | F25: MICHAEL | G25: JENSEN | M25: RETA OP FIN | O25: SOLD | P25: 325000 | Q25: =P25*$U$3 -> 6012500 | R25: 162500 | T25: =P25-R25 -> 162500 | U25: =T25*U$3 -> 3006250 | W25: CREDITO RETA | X25: =VLOOKUP(C25,Banorte!F:K,6,FALSE) -> #N/A | Z25: =X25-Y25 -> #N/A | AI25: 46265 | AO25: V19 | AP25: 46227 | AQ25: 46265 | AR25: RETA OP FIN
B26: 164 | C26: 20 | D26: MXN | F26: ADAN | G26: MARTINEZ | H26: VILLA | M26: GENERAL | O26: SOLD | Q26: 10308375 | S26: 7308375 | U26: =Q26-S26 -> 3000000 | X26: =VLOOKUP(C26,Banorte!F:K,6,FALSE) -> #N/A | Z26: =X26-Y26 -> #N/A | AI26: 46265 | AO26: V20 | AP26: 46227 | AQ26: 46265 | AR26: GENERAL
B27: 165 | C27: 21 | D27: MXN | M27: GENERAL | O27: AVAILABLE | U27: =Q27-S27 -> 0 | X27: =VLOOKUP(C27,Banorte!F:K,6,FALSE) -> #N/A | Z27: =X27-Y27 -> #N/A | AI27: 46265 | AO27: V21 | AP27: 46227 | AQ27: 46265 | AR27: GENERAL | AS27: DISPONIBLE
B28: 10 | C28: 301 | D28: USD | F28: GERARD j | G28: HEALEY | M28: RETA OP FIN | O28: SOLD | P28: 209800 | Q28: =P28*$U$3 -> 3881300 | R28: 83916 | T28: =P28-R28 -> 125884 | U28: =T28*U$3 -> 2328854 | W28: CREDITO RETA | X28: =VLOOKUP(C28,Banorte!F:K,6,FALSE) -> #N/A | Z28: =X28-Y28 -> #N/A | AI28: 46244 | AO28: 301 | AP28: 46213 | AQ28: 46244 | AR28: RETA OP FIN
B29: 11 | C29: 302 | D29: USD | F29: CRAIG OLIVER | G29: CHRISTIANSON | M29: RETA OP FIN | O29: SOLD | P29: 209800 | Q29: =P29*$U$3 -> 3881300 | R29: 83918 | T29: =P29-R29 -> 125882 | U29: =T29*U$3 -> 2328817 | W29: CREDITO RETA | X29: =VLOOKUP(C29,Banorte!F:K,6,FALSE) -> #N/A | Z29: =X29-Y29 -> #N/A | AI29: 46244 | AO29: 302 | AP29: 46213 | AQ29: 46244 | AR29: RETA OP FIN
B30: 12 | C30: 303 | D30: USD | F30: VINCENT | G30: FONSECA | M30: RETA OP FIN | O30: SOLD | P30: 209800 | Q30: =P30*$U$3 -> 3881300 | R30: 83916 | T30: =P30-R30 -> 125884 | U30: =T30*U$3 -> 2328854 | W30: CREDITO RETA | X30: =VLOOKUP(C30,Banorte!F:K,6,FALSE) -> #N/A | Z30: =X30-Y30 -> #N/A | AI30: 46244 | AO30: 303 | AP30: 46213 | AQ30: 46244 | AR30: RETA OP FIN
B31: 166 | C31: 304 | D31: MXN | F31: CAMERON ARTHUR | G31: WILKES | M31: GENERAL | O31: SOLD | Q31: 8549000 | S31: 8549000 | U31: =Q31-S31 -> 0 | X31: =VLOOKUP(C31,Banorte!F:K,6,FALSE) -> #N/A | Z31: =X31-Y31 -> #N/A | AI31: 46244 | AO31: 304 | AP31: 46213 | AQ31: 46244 | AR31: GENERAL | AS31: PAGADO
B32: 13 | C32: 305 | D32: USD | F32: JOHN WAYLAND | G32: SLAUGHTER | M32: RETA OP FIN | O32: SOLD | P32: 363500 | Q32: =P32*$U$3 -> 6724750 | R32: 130920 | T32: =P32-R32 -> 232580 | U32: =T32*U$3 -> 4302730 | W32: CREDITO RETA | X32: =VLOOKUP(C32,Banorte!F:K,6,FALSE) -> #N/A | Z32: =X32-Y32 -> #N/A | AI32: 46244 | AO32: 305 | AP32: 46213 | AQ32: 46244 | AR32: RETA OP FIN
B33: 14 | C33: 306 | D33: USD | F33: CAROL ANN | G33: ROBERTS | M33: RETA OP FIN | O33: SOLD | P33: 209800 | Q33: =P33*$U$3 -> 3881300 | R33: 83916 | T33: =P33-R33 -> 125884 | U33: =T33*U$3 -> 2328854 | W33: CREDITO RETA | X33: =VLOOKUP(C33,Banorte!F:K,6,FALSE) -> #N/A | Z33: =X33-Y33 -> #N/A | AI33: 46244 | AO33: 306 | AP33: 46213 | AQ33: 46244 | AR33: RETA OP FIN
B34: 15 | C34: 307 | D34: USD | F34: RANDY NEIL | G34: YEAGER | M34: RETA OP FIN | O34: SOLD | P34: 209800 | Q34: =P34*$U$3 -> 3881300 | R34: 83916 | T34: =P34-R34 -> 125884 | U34: =T34*U$3 -> 2328854 | W34: CREDITO RETA | X34: =VLOOKUP(C34,Banorte!F:K,6,FALSE) -> #N/A | Z34: =X34-Y34 -> #N/A | AI34: 46244 | AO34: 307 | AP34: 46213 | AQ34: 46244 | AR34: RETA OP FIN
B35: 16 | C35: 308 | D35: USD | F35: Robert Glenn | G35: GOOGE | M35: RETA | O35: SOLD | P35: 209800 | Q35: =P35*$U$3 -> 3881300 | R35: 83916 | T35: =P35-R35 -> 125884 | U35: =T35*U$3 -> 2328854 | X35: =VLOOKUP(C35,Banorte!F:K,6,FALSE) -> #N/A | Z35: =X35-Y35 -> #N/A | AI35: 46244 | AO35: 308 | AP35: 46213 | AQ35: 46244 | AR35: RETA
B36: 17 | C36: 309 | D36: USD | F36: JORGE | G36: QUINONES VELEZ | M36: RETA OP FIN | O36: SOLD | P36: 209800 | Q36: =P36*$U$3 -> 3881300 | R36: 83916 | T36: =P36-R36 -> 125884 | U36: =T36*U$3 -> 2328854 | W36: CREDITO RETA | X36: =VLOOKUP(C36,Banorte!F:K,6,FALSE) -> #N/A | Z36: =X36-Y36 -> #N/A | AI36: 46244 | AO36: 309 | AP36: 46213 | AQ36: 46244 | AR36: RETA OP FIN
B37: 18 | C37: 310 | D37: USD | F37: JOSEPH LEONARD | G37: UMIDI | M37: RETA | O37: SOLD | P37: 209800 | Q37: =P37*$U$3 -> 3881300 | R37: 83916 | T37: =P37-R37 -> 125884 | U37: =T37*U$3 -> 2328854 | X37: =VLOOKUP(C37,Banorte!F:K,6,FALSE) -> #N/A | Z37: =X37-Y37 -> #N/A | AI37: 46244 | AO37: 310 | AP37: 46213 | AQ37: 46244 | AR37: RETA
B38: 19 | C38: 311 | D38: USD | F38: NICK DELANO | G38: DE BARMORE | M38: RETA OP FIN | O38: SOLD | P38: 209800 | Q38: =P38*$U$3 -> 3881300 | R38: 199310 | T38: =P38-R38 -> 10490 | U38: =T38*U$3 -> 194065 | W38: CREDITO RETA | X38: =VLOOKUP(C38,Banorte!F:K,6,FALSE) -> #N/A | Z38: =X38-Y38 -> #N/A | AI38: 46244 | AO38: 311 | AP38: 46213 | AQ38: 46244 | AR38: RETA OP FIN | AS38: PAGADO
B39: 20 | C39: 312 | D39: USD | F39: DANNIEL JOHN | G39: JOHNSON | M39: RETA OP FIN | O39: SOLD | P39: 209800 | Q39: =P39*$U$3 -> 3881300 | R39: 83916 | T39: =P39-R39 -> 125884 | U39: =T39*U$3 -> 2328854 | W39: CREDITO RETA | X39: =VLOOKUP(C39,Banorte!F:K,6,FALSE) -> #N/A | Z39: =X39-Y39 -> #N/A | AI39: 46244 | AO39: 312 | AP39: 46213 | AQ39: 46244 | AR39: RETA OP FIN
B40: 21 | C40: 313 | D40: USD | F40: MICHAEL DAVID | G40: LENKER | M40: RETA OP FIN | O40: SOLD | P40: 363500 | Q40: =P40*$U$3 -> 6724750 | R40: 130920 | T40: =P40-R40 -> 232580 | U40: =T40*U$3 -> 4302730 | W40: CREDITO RETA | X40: =VLOOKUP(C40,Banorte!F:K,6,FALSE) -> #N/A | Z40: =X40-Y40 -> #N/A | AI40: 46244 | AO40: 313 | AP40: 46213 | AQ40: 46244 | AR40: RETA OP FIN
B41: 22 | C41: 314 | D41: USD | F41: CARMINE | G41: MITRONI | M41: RETA OP FIN | O41: SOLD | P41: 363500 | Q41: =P41*$U$3 -> 6724750 | R41: 362965 | T41: =P41-R41 -> 535 | U41: =T41*U$3 -> 9897.5 | W41: CREDITO RETA | X41: =VLOOKUP(C41,Banorte!F:K,6,FALSE) -> #N/A | Z41: =X41-Y41 -> #N/A | AI41: 46244 | AO41: 314 | AP41: 46213 | AQ41: 46244 | AR41: RETA OP FIN | AS41: PAGADO
B42: 23 | C42: 315 | D42: USD | F42: EDWARD PAUL | G42: KOZEK | M42: RETA OP FIN | O42: SOLD | P42: 209800 | Q42: =P42*$U$3 -> 3881300 | R42: 83916 | T42: =P42-R42 -> 125884 | U42: =T42*U$3 -> 2328854 | W42: CREDITO RETA | X42: =VLOOKUP(C42,Banorte!F:K,6,FALSE) -> #N/A | Z42: =X42-Y42 -> #N/A | AI42: 46244 | AO42: 315 | AP42: 46213 | AQ42: 46244 | AR42: RETA OP FIN
B43: 24 | C43: 316 | D43: USD | F43: KIRSTEN LEIGH | G43: HELD | M43: RETA OP FIN | O43: SOLD | P43: 209800 | Q43: =P43*$U$3 -> 3881300 | R43: 83916 | T43: =P43-R43 -> 125884 | U43: =T43*U$3 -> 2328854 | W43: CREDITO RETA | X43: =VLOOKUP(C43,Banorte!F:K,6,FALSE) -> #N/A | Z43: =X43-Y43 -> #N/A | AI43: 46244 | AO43: 316 | AP43: 46213 | AQ43: 46244 | AR43: RETA OP FIN
B44: 25 | C44: 317 | D44: USD | F44: NIKI | G44: PASRICHA | M44: RETA OP FIN | O44: SOLD | P44: 209800 | Q44: =P44*$U$3 -> 3881300 | R44: 122166 | T44: =P44-R44 -> 87634 | U44: =T44*U$3 -> 1621229 | W44: CREDITO RETA | X44: =VLOOKUP(C44,Banorte!F:K,6,FALSE) -> #N/A | Z44: =X44-Y44 -> #N/A | AI44: 46244 | AO44: 317 | AP44: 46213 | AQ44: 46244 | AR44: RETA OP FIN
B45: 167 | C45: 401 | D45: MXN | F45: FRANCISCO JAVIER | G45: FLORES | H45: RODRIGUEZ | M45: GENERAL | O45: SOLD | Q45: 7750000 | S45: 2325000 | U45: =Q45-S45 -> 5425000 | X45: =VLOOKUP(C45,Banorte!F:K,6,FALSE) -> #N/A | Z45: =X45-Y45 -> #N/A | AI45: 46188 | AO45: 401 | AP45: 46157 | AQ45: 46188 | AR45: GENERAL
B46: 26 | C46: 402 | D46: USD | F46: PATRISHA LYNN | G46: EDGERTON | M46: RETA OP FIN | O46: SOLD | P46: 216900 | Q46: =P46*$U$3 -> 4012650 | R46: 86767 | T46: =P46-R46 -> 130133 | U46: =T46*U$3 -> 2407460.5 | W46: CREDITO RETA | X46: =VLOOKUP(C46,Banorte!F:K,6,FALSE) -> #N/A | Z46: =X46-Y46 -> #N/A | AI46: 46188 | AO46: 402 | AP46: 46157 | AQ46: 46188 | AR46: RETA OP FIN
B47: 27 | C47: 403 | D47: USD | F47: PAMELA ANNE | G47: SCHNEIDER | M47: RETA OP FIN | O47: SOLD | P47: 216900 | Q47: =P47*$U$3 -> 4012650 | R47: 86767 | T47: =P47-R47 -> 130133 | U47: =T47*U$3 -> 2407460.5 | W47: CREDITO RETA | X47: =VLOOKUP(C47,Banorte!F:K,6,FALSE) -> #N/A | Z47: =X47-Y47 -> #N/A | AI47: 46188 | AO47: 403 | AP47: 46157 | AQ47: 46188 | AR47: RETA OP FIN
B48: 168 | C48: 404 | D48: MXN | F48: JORGE ADOLFO JOSE | G48: BASTARRACHEA | H48: ORTIZ | M48: GENERAL | O48: SOLD | Q48: 8202600 | S48: 5741820 | U48: =Q48-S48 -> 2460780 | X48: =VLOOKUP(C48,Banorte!F:K,6,FALSE) -> #N/A | Z48: =X48-Y48 -> #N/A | AI48: 46188 | AO48: 404 | AP48: 46157 | AQ48: 46188 | AR48: GENERAL
B49: 28 | C49: 405 | D49: USD | F49: PATRICK louis | G49: NALLY | M49: RETA OP FIN | O49: SOLD | P49: 367000 | Q49: =P49*$U$3 -> 6789500 | R49: 131620 | T49: =P49-R49 -> 235380 | U49: =T49*U$3 -> 4354530 | W49: CREDITO RETA | X49: =VLOOKUP(C49,Banorte!F:K,6,FALSE) -> #N/A | Z49: =X49-Y49 -> #N/A | AI49: 46188 | AO49: 405 | AP49: 46157 | AQ49: 46188 | AR49: RETA OP FIN
B50: 29 | C50: 406 | D50: USD | F50: CLAYTON L | G50: BRANUM | M50: RETA | O50: SOLD | P50: 216900 | Q50: =P50*$U$3 -> 4012650 | R50: 86767 | T50: =P50-R50 -> 130133 | U50: =T50*U$3 -> 2407460.5 | X50: =VLOOKUP(C50,Banorte!F:K,6,FALSE) -> #N/A | Z50: =X50-Y50 -> #N/A | AI50: 46188 | AO50: 406 | AP50: 46157 | AQ50: 46188 | AR50: RETA
B51: 30 | C51: 407 | D51: USD | F51: THOMAS CHARLES | G51: DUNNE | M51: RETA OP FIN | O51: SOLD | P51: 216900 | Q51: =P51*$U$3 -> 4012650 | R51: 86767 | T51: =P51-R51 -> 130133 | U51: =T51*U$3 -> 2407460.5 | W51: CREDITO RETA | X51: =VLOOKUP(C51,Banorte!F:K,6,FALSE) -> #N/A | Z51: =X51-Y51 -> #N/A | AI51: 46188 | AO51: 407 | AP51: 46157 | AQ51: 46188 | AR51: RETA OP FIN
B52: 31 | C52: 408 | D52: USD | F52: JAMES ROBERT | G52: MC GONNELL | M52: RETA OP FIN | O52: SOLD | P52: 216900 | Q52: =P52*$U$3 -> 4012650 | R52: 86767 | T52: =P52-R52 -> 130133 | U52: =T52*U$3 -> 2407460.5 | W52: CREDITO RETA | X52: =VLOOKUP(C52,Banorte!F:K,6,FALSE) -> #N/A | Z52: =X52-Y52 -> #N/A | AI52: 46188 | AO52: 408 | AP52: 46157 | AQ52: 46188 | AR52: RETA OP FIN
B53: 169 | C53: 409 | D53: MXN | F53: MONIQUE ram | G53: HARITZALDE | M53: GENERAL | O53: SOLD | Q53: 7727775 | S53: 6255874.3 | U53: =Q53-S53 -> 1471900.7 | X53: =VLOOKUP(C53,Banorte!F:K,6,FALSE) -> #N/A | Z53: =X53-Y53 -> #N/A | AI53: 46188 | AO53: 409 | AP53: 46157 | AQ53: 46188 | AR53: GENERAL
B54: 32 | C54: 410 | D54: USD | F54: DECLAN RONAN | G54: O'CLEIRIGH | M54: RETA | O54: SOLD | P54: 216900 | Q54: =P54*$U$3 -> 4012650 | R54: 86767 | T54: =P54-R54 -> 130133 | U54: =T54*U$3 -> 2407460.5 | X54: =VLOOKUP(C54,Banorte!F:K,6,FALSE) -> #N/A | Z54: =X54-Y54 -> #N/A | AI54: 46188 | AO54: 410 | AP54: 46157 | AQ54: 46188 | AR54: RETA
B55: 33 | C55: 411 | D55: USD | F55: MICHAEL | G55: SANTA GUIDA | M55: RETA OP FIN | O55: SOLD | P55: 216900 | Q55: =P55*$U$3 -> 4012650 | R55: 86757 | T55: =P55-R55 -> 130143 | U55: =T55*U$3 -> 2407645.5 | W55: CREDITO RETA | X55: =VLOOKUP(C55,Banorte!F:K,6,FALSE) -> #N/A | Z55: =X55-Y55 -> #N/A | AI55: 46188 | AO55: 411 | AP55: 46157 | AQ55: 46188 | AR55: RETA OP FIN
B56: 34 | C56: 412 | D56: USD | F56: JAMES ALLEN | G56: ANTONICK | M56: RETA | O56: SOLD | P56: 216900 | Q56: =P56*$U$3 -> 4012650 | R56: 86767 | T56: =P56-R56 -> 130133 | U56: =T56*U$3 -> 2407460.5 | X56: =VLOOKUP(C56,Banorte!F:K,6,FALSE) -> #N/A | Z56: =X56-Y56 -> #N/A | AI56: 46188 | AO56: 412 | AP56: 46157 | AQ56: 46188 | AR56: RETA
B57: 170 | C57: 413 | D57: MXN | F57: JEFFREY alexander | G57: BRIDE | M57: GENERAL | O57: SOLD | Q57: 12350000 | S57: 9973320.8 | U57: =Q57-S57 -> 2376679.2 | X57: =VLOOKUP(C57,Banorte!F:K,6,FALSE) -> #N/A | Z57: =X57-Y57 -> #N/A | AI57: 46188 | AO57: 413 | AP57: 46157 | AQ57: 46188 | AR57: GENERAL
B58: 35 | C58: 414 | D58: USD | F58: ZANDRA | G58: JONES | M58: RETA OP FIN | O58: SOLD | P58: 367000 | Q58: =P58*$U$3 -> 6789500 | R58: 131620 | T58: =P58-R58 -> 235380 | U58: =T58*U$3 -> 4354530 | W58: CREDITO RETA | X58: =VLOOKUP(C58,Banorte!F:K,6,FALSE) -> #N/A | Z58: =X58-Y58 -> #N/A | AI58: 46188 | AO58: 414 | AP58: 46157 | AQ58: 46188 | AR58: RETA OP FIN
B59: 36 | C59: 415 | D59: USD | F59: RAYMOND PAUL | G59: DETHLOFF jr | M59: RETA | O59: SOLD | P59: 216900 | Q59: =P59*$U$3 -> 4012650 | R59: 110489 | T59: =P59-R59 -> 106411 | U59: =T59*U$3 -> 1968603.5 | X59: =VLOOKUP(C59,Banorte!F:K,6,FALSE) -> #N/A | Z59: =X59-Y59 -> #N/A | AI59: 46188 | AO59: 415 | AP59: 46157 | AQ59: 46188 | AR59: RETA
B60: 37 | C60: 416 | D60: USD | F60: BRIAN DANIEL | G60: BAILEY | M60: RETA OP FIN | O60: SOLD | P60: 216900 | Q60: =P60*$U$3 -> 4012650 | R60: 86767 | T60: =P60-R60 -> 130133 | U60: =T60*U$3 -> 2407460.5 | W60: CREDITO RETA | X60: =VLOOKUP(C60,Banorte!F:K,6,FALSE) -> #N/A | Z60: =X60-Y60 -> #N/A | AI60: 46188 | AO60: 416 | AP60: 46157 | AQ60: 46188 | AR60: RETA OP FIN
B61: 38 | C61: 417 | D61: USD | F61: SUSAN KNAUSE | G61: PETRICK | M61: RETA OP FIN | O61: SOLD | P61: 216900 | Q61: =P61*$U$3 -> 4012650 | R61: 108449 | T61: =P61-R61 -> 108451 | U61: =T61*U$3 -> 2006343.5 | W61: CREDITO RETA | X61: =VLOOKUP(C61,Banorte!F:K,6,FALSE) -> #N/A | Z61: =X61-Y61 -> #N/A | AI61: 46188 | AO61: 417 | AP61: 46157 | AQ61: 46188 | AR61: RETA OP FIN
B62: 39 | C62: 501 | D62: USD | F62: RUSSELL ARTHUR | G62: GLENN | M62: RETA | O62: SOLD | P62: 216900 | Q62: =P62*$U$3 -> 4012650 | R62: 86767 | T62: =P62-R62 -> 130133 | U62: =T62*U$3 -> 2407460.5 | X62: =VLOOKUP(C62,Banorte!F:K,6,FALSE) -> #N/A | Z62: =X62-Y62 -> #N/A | AI62: 46170 | AO62: 501 | AP62: 46080 | AQ62: 46170 | AR62: RETA
B63: 40 | C63: 502 | D63: USD | F63: GREGORY EDWARD | G63: PEACOCK | M63: RETA OP FIN | O63: SOLD | P63: 216900 | Q63: =P63*$U$3 -> 4012650 | R63: 86767 | T63: =P63-R63 -> 130133 | U63: =T63*U$3 -> 2407460.5 | W63: CREDITO RETA | X63: =VLOOKUP(C63,Banorte!F:K,6,FALSE) -> #N/A | Z63: =X63-Y63 -> #N/A | AI63: 46170 | AO63: 502 | AP63: 46080 | AQ63: 46170 | AR63: RETA OP FIN
B64: 41 | C64: 503 | D64: USD | F64: RICHARD | G64: NATELSON | M64: RETA | O64: SOLD | P64: 216900 | Q64: =P64*$U$3 -> 4012650 | R64: 86767 | T64: =P64-R64 -> 130133 | U64: =T64*U$3 -> 2407460.5 | X64: =VLOOKUP(C64,Banorte!F:K,6,FALSE) -> #N/A | Z64: =X64-Y64 -> #N/A | AI64: 46170 | AO64: 503 | AP64: 46080 | AQ64: 46170 | AR64: RETA
B65: 171 | C65: 504 | D65: MXN | F65: HECTOR CESAR | G65: DURAN | H65: VEGA | M65: GENERAL | O65: SOLD | Q65: 8271200 | S65: 8271200 | U65: =Q65-S65 -> 0 | X65: =VLOOKUP(C65,Banorte!F:K,6,FALSE) -> #N/A | Z65: =X65-Y65 -> #N/A | AI65: 46170 | AO65: 504 | AP65: 46080 | AQ65: 46170 | AR65: GENERAL | AS65: PAGADO
B66: 42 | C66: 505 | D66: USD | F66: HENRY JOHN | G66: KUNKEL | M66: RETA OP FIN | O66: SOLD | P66: 370500 | Q66: =P66*$U$3 -> 6854250 | R66: 132320 | T66: =P66-R66 -> 238180 | U66: =T66*U$3 -> 4406330 | W66: CREDITO RETA | X66: =VLOOKUP(C66,Banorte!F:K,6,FALSE) -> #N/A | Z66: =X66-Y66 -> #N/A | AI66: 46170 | AO66: 505 | AP66: 46080 | AQ66: 46170 | AR66: RETA OP FIN
B67: 43 | C67: 506 | D67: USD | F67: ZACHARY ADAM | G67: CIHAK | M67: RETA OP FIN | O67: SOLD | P67: 216900 | Q67: =P67*$U$3 -> 4012650 | R67: 86767 | T67: =P67-R67 -> 130133 | U67: =T67*U$3 -> 2407460.5 | W67: CREDITO RETA | X67: =VLOOKUP(C67,Banorte!F:K,6,FALSE) -> #N/A | Z67: =X67-Y67 -> #N/A | AI67: 46170 | AO67: 506 | AP67: 46080 | AQ67: 46170 | AR67: RETA OP FIN
B68: 44 | C68: 507 | D68: USD | F68: THOMAS SHAWN | G68: GRADY | M68: RETA OP FIN | O68: SOLD | P68: 216900 | Q68: =P68*$U$3 -> 4012650 | R68: 86667 | T68: =P68-R68 -> 130233 | U68: =T68*U$3 -> 2409310.5 | W68: CREDITO RETA | X68: =VLOOKUP(C68,Banorte!F:K,6,FALSE) -> #N/A | Z68: =X68-Y68 -> #N/A | AI68: 46170 | AO68: 507 | AP68: 46080 | AQ68: 46170 | AR68: RETA OP FIN
B69: 45 | C69: 508 | D69: USD | F69: MARVIN MERLE | G69: NEWTON III | M69: RETA OP FIN | O69: SOLD | P69: 216900 | Q69: =P69*$U$3 -> 4012650 | R69: 216400 | T69: =P69-R69 -> 500 | U69: =T69*U$3 -> 9250 | W69: CREDITO RETA | X69: =VLOOKUP(C69,Banorte!F:K,6,FALSE) -> #N/A | Z69: =X69-Y69 -> #N/A | AI69: 46170 | AO69: 508 | AP69: 46080 | AQ69: 46170 | AR69: RETA OP FIN | AS69: PAGADO
B70: 46 | C70: 509 | D70: USD | F70: RAYMOND HIROSHI | G70: AKA | M70: RETA OP FIN | O70: SOLD | P70: 216900 | Q70: =P70*$U$3 -> 4012650 | R70: 108450 | T70: =P70-R70 -> 108450 | U70: =T70*U$3 -> 2006325 | W70: CREDITO RETA | X70: =VLOOKUP(C70,Banorte!F:K,6,FALSE) -> #N/A | Z70: =X70-Y70 -> #N/A | AI70: 46170 | AO70: 509 | AP70: 46080 | AQ70: 46170 | AR70: RETA OP FIN
B71: 47 | C71: 510 | D71: USD | F71: MICHAEL | G71: SHAH | M71: RETA | O71: SOLD | P71: 216900 | Q71: =P71*$U$3 -> 4012650 | R71: 86767 | T71: =P71-R71 -> 130133 | U71: =T71*U$3 -> 2407460.5 | X71: =VLOOKUP(C71,Banorte!F:K,6,FALSE) -> #N/A | Z71: =X71-Y71 -> #N/A | AI71: 46170 | AO71: 510 | AP71: 46080 | AQ71: 46170 | AR71: RETA
B72: 48 | C72: 511 | D72: USD | F72: MICHAEL stephen | G72: GRIFFITH | M72: RETA | O72: SOLD | P72: 216900 | Q72: =P72*$U$3 -> 4012650 | R72: 96767 | T72: =P72-R72 -> 120133 | U72: =T72*U$3 -> 2222460.5 | X72: =VLOOKUP(C72,Banorte!F:K,6,FALSE) -> #N/A | Z72: =X72-Y72 -> #N/A | AI72: 46170 | AO72: 511 | AP72: 46080 | AQ72: 46170 | AR72: RETA
B73: 49 | C73: 512 | D73: USD | F73: TROY ALAN | G73: MILLS | M73: RETA OP FIN | O73: SOLD | P73: 216900 | Q73: =P73*$U$3 -> 4012650 | R73: 86767 | T73: =P73-R73 -> 130133 | U73: =T73*U$3 -> 2407460.5 | W73: CREDITO RETA | X73: =VLOOKUP(C73,Banorte!F:K,6,FALSE) -> #N/A | Z73: =X73-Y73 -> #N/A | AI73: 46170 | AO73: 512 | AP73: 46080 | AQ73: 46170 | AR73: RETA OP FIN
B74: 172 | C74: 513 | D74: MXN | F74: PATRICIA | G74: LOZANO | H74: MEADE | M74: GENERAL | O74: SOLD | Q74: 9362700 | S74: 2808810 | U74: =Q74-S74 -> 6553890 | X74: =VLOOKUP(C74,Banorte!F:K,6,FALSE) -> #N/A | Z74: =X74-Y74 -> #N/A | AI74: 46170 | AO74: 513 | AP74: 46080 | AQ74: 46170 | AR74: GENERAL
B75: 173 | C75: 514 | D75: MXN | M75: GENERAL | O75: AVAILABLE | U75: =Q75-S75 -> 0 | X75: =VLOOKUP(C75,Banorte!F:K,6,FALSE) -> #N/A | Z75: =X75-Y75 -> #N/A | AI75: 46170 | AO75: 514 | AP75: 46080 | AQ75: 46170 | AR75: GENERAL | AS75: DISPONIBLE
B76: 50 | C76: 515 | D76: USD | F76: SYLVIA AMY | G76: SCHAFER | M76: RETA OP FIN | O76: SOLD | P76: 216900 | Q76: =P76*$U$3 -> 4012650 | R76: 86767 | T76: =P76-R76 -> 130133 | U76: =T76*U$3 -> 2407460.5 | W76: CREDITO RETA | X76: =VLOOKUP(C76,Banorte!F:K,6,FALSE) -> #N/A | Z76: =X76-Y76 -> #N/A | AI76: 46170 | AO76: 515 | AP76: 46080 | AQ76: 46170 | AR76: RETA OP FIN
B77: 51 | C77: 516 | D77: USD | F77: CONSTANTINOS | G77: KRASHIAS | M77: RETA OP FIN | O77: SOLD | P77: 216900 | Q77: =P77*$U$3 -> 4012650 | R77: 108450 | T77: =P77-R77 -> 108450 | U77: =T77*U$3 -> 2006325 | W77: CREDITO RETA | X77: =VLOOKUP(C77,Banorte!F:K,6,FALSE) -> #N/A | Z77: =X77-Y77 -> #N/A | AI77: 46170 | AO77: 516 | AP77: 46080 | AQ77: 46170 | AR77: RETA OP FIN
B78: 52 | C78: 517 | D78: USD | F78: MICHAEL COLLINS | G78: WAGNER | M78: RETA OP FIN | O78: SOLD | P78: 216900 | Q78: =P78*$U$3 -> 4012650 | R78: 88171 | T78: =P78-R78 -> 128729 | U78: =T78*U$3 -> 2381486.5 | W78: CREDITO RETA | X78: =VLOOKUP(C78,Banorte!F:K,6,FALSE) -> #N/A | Z78: =X78-Y78 -> #N/A | AI78: 46170 | AO78: 517 | AP78: 46080 | AQ78: 46170 | AR78: RETA OP FIN
B79: 53 | C79: 601 | D79: USD | F79: MICHAEL JAMES | G79: GOLDSMITH | M79: RETA OP FIN | O79: SOLD | P79: 216900 | Q79: =P79*$U$3 -> 4012650 | R79: 86767 | T79: =P79-R79 -> 130133 | U79: =T79*U$3 -> 2407460.5 | W79: CREDITO RETA | X79: =VLOOKUP(C79,Banorte!F:K,6,FALSE) -> #N/A | Z79: =X79-Y79 -> #N/A | AI79: 46170 | AO79: 601 | AP79: 46108 | AQ79: 46170 | AR79: RETA OP FIN
B80: 54 | C80: 602 | D80: USD | F80: CHARLES DAVID | G80: WILDER | M80: RETA OP FIN | O80: SOLD | P80: 216900 | Q80: =P80*$U$3 -> 4012650 | R80: 86767 | T80: =P80-R80 -> 130133 | U80: =T80*U$3 -> 2407460.5 | W80: CREDITO RETA | X80: =VLOOKUP(C80,Banorte!F:K,6,FALSE) -> #N/A | Z80: =X80-Y80 -> #N/A | AI80: 46170 | AO80: 602 | AP80: 46108 | AQ80: 46170 | AR80: RETA OP FIN
B81: 55 | C81: 603 | D81: USD | F81: KATHERINE | G81: DARLING | M81: RETA OP FIN | O81: SOLD | P81: 216900 | Q81: =P81*$U$3 -> 4012650 | R81: 75638 | T81: =P81-R81 -> 141262 | U81: =T81*U$3 -> 2613347 | W81: CREDITO RETA | X81: =VLOOKUP(C81,Banorte!F:K,6,FALSE) -> #N/A | Z81: =X81-Y81 -> #N/A | AI81: 46170 | AO81: 603 | AP81: 46108 | AQ81: 46170 | AR81: RETA OP FIN
B82: 56 | C82: 604 | D82: USD | F82: VALERIE LYNN | G82: DORSETT | M82: RETA OP FIN | O82: SOLD | P82: 374000 | Q82: =P82*$U$3 -> 6919000 | R82: 142095 | T82: =P82-R82 -> 231905 | U82: =T82*U$3 -> 4290242.5 | W82: CREDITO RETA | X82: =VLOOKUP(C82,Banorte!F:K,6,FALSE) -> #N/A | Z82: =X82-Y82 -> #N/A | AI82: 46170 | AO82: 604 | AP82: 46108 | AQ82: 46170 | AR82: RETA OP FIN
B83: 57 | C83: 605 | D83: USD | F83: ROBERT ANTHONY | G83: PALMA | M83: RETA OP FIN | O83: SOLD | P83: 374000 | Q83: =P83*$U$3 -> 6919000 | R83: 255220 | T83: =P83-R83 -> 118780 | U83: =T83*U$3 -> 2197430 | W83: CREDITO RETA | X83: =VLOOKUP(C83,Banorte!F:K,6,FALSE) -> #N/A | Z83: =X83-Y83 -> #N/A | AI83: 46170 | AO83: 605 | AP83: 46108 | AQ83: 46170 | AR83: RETA OP FIN
B84: 58 | C84: 606 | D84: USD | F84: DAVID kenneth | G84: MCDONALD | M84: RETA OP FIN | O84: SOLD | P84: 216900 | Q84: =P84*$U$3 -> 4012650 | R84: 86767 | T84: =P84-R84 -> 130133 | U84: =T84*U$3 -> 2407460.5 | W84: CREDITO RETA | X84: =VLOOKUP(C84,Banorte!F:K,6,FALSE) -> #N/A | Z84: =X84-Y84 -> #N/A | AI84: 46170 | AO84: 606 | AP84: 46108 | AQ84: 46170 | AR84: RETA OP FIN
B85: 59 | C85: 607 | D85: USD | F85: EDWIN DEAN | G85: SCHUYLER | M85: RETA | O85: SOLD | P85: 216900 | Q85: =P85*$U$3 -> 4012650 | R85: 109950 | T85: =P85-R85 -> 106950 | U85: =T85*U$3 -> 1978575 | X85: =VLOOKUP(C85,Banorte!F:K,6,FALSE) -> #N/A | Z85: =X85-Y85 -> #N/A | AI85: 46170 | AO85: 607 | AP85: 46108 | AQ85: 46170 | AR85: RETA
B86: 60 | C86: 608 | D86: USD | F86: FAIZAL | G86: DHALLA | M86: RETA OP FIN | O86: SOLD | P86: 216900 | Q86: =P86*$U$3 -> 4012650 | R86: 101749 | T86: =P86-R86 -> 115151 | U86: =T86*U$3 -> 2130293.5 | W86: CREDITO RETA | X86: =VLOOKUP(C86,Banorte!F:K,6,FALSE) -> #N/A | Z86: =X86-Y86 -> #N/A | AI86: 46170 | AO86: 608 | AP86: 46108 | AQ86: 46170 | AR86: RETA OP FIN
B87: 61 | C87: 609 | D87: USD | F87: CYNTHIA MARY | G87: DICKINS COLLIN SMITH | M87: RETA OP FIN | O87: SOLD | P87: 216900 | Q87: =P87*$U$3 -> 4012650 | R87: 86767 | T87: =P87-R87 -> 130133 | U87: =T87*U$3 -> 2407460.5 | W87: CREDITO RETA | X87: =VLOOKUP(C87,Banorte!F:K,6,FALSE) -> #N/A | Z87: =X87-Y87 -> #N/A | AI87: 46170 | AO87: 609 | AP87: 46108 | AQ87: 46170 | AR87: RETA OP FIN
B88: 62 | C88: 610 | D88: USD | F88: CRAIG WILLIAM | G88: BEAL | M88: RETA OP FIN | O88: SOLD | P88: 216900 | Q88: =P88*$U$3 -> 4012650 | R88: 86767 | T88: =P88-R88 -> 130133 | U88: =T88*U$3 -> 2407460.5 | W88: CREDITO RETA | X88: =VLOOKUP(C88,Banorte!F:K,6,FALSE) -> #N/A | Z88: =X88-Y88 -> #N/A | AI88: 46170 | AO88: 610 | AP88: 46108 | AQ88: 46170 | AR88: RETA OP FIN
B89: 63 | C89: 611 | D89: USD | F89: LEE SHERRY | G89: LAUGHMAN | M89: RETA | O89: SOLD | P89: 216900 | Q89: =P89*$U$3 -> 4012650 | R89: 86767 | T89: =P89-R89 -> 130133 | U89: =T89*U$3 -> 2407460.5 | X89: =VLOOKUP(C89,Banorte!F:K,6,FALSE) -> #N/A | Z89: =X89-Y89 -> #N/A | AI89: 46170 | AO89: 611 | AP89: 46108 | AQ89: 46170 | AR89: RETA
B90: 64 | C90: 612 | D90: USD | F90: JOSEPH GERALD | G90: SPRINGER | M90: RETA OP FIN | O90: SOLD | P90: 216900 | Q90: =P90*$U$3 -> 4012650 | R90: 86767 | T90: =P90-R90 -> 130133 | U90: =T90*U$3 -> 2407460.5 | W90: CREDITO RETA | X90: =VLOOKUP(C90,Banorte!F:K,6,FALSE) -> #N/A | Z90: =X90-Y90 -> #N/A | AI90: 46170 | AO90: 612 | AP90: 46108 | AQ90: 46170 | AR90: RETA OP FIN
B91: 174 | C91: 613 | D91: MXN | F91: MANUEL ENRIQUE | G91: GARCIA | H91: GARZA | M91: GENERAL | O91: SOLD | Q91: 9006200 | S91: 2701860 | U91: =Q91-S91 -> 6304340 | X91: =VLOOKUP(C91,Banorte!F:K,6,FALSE) -> #N/A | Z91: =X91-Y91 -> #N/A | AI91: 46170 | AO91: 613 | AP91: 46108 | AQ91: 46170 | AR91: GENERAL
B92: 65 | C92: 614 | D92: USD | F92: THOMAS TEOFIL | G92: HRUSOVSKY | M92: RETA OP FIN | O92: SOLD | P92: 374000 | Q92: =P92*$U$3 -> 6919000 | R92: 133020 | T92: =P92-R92 -> 240980 | U92: =T92*U$3 -> 4458130 | W92: CREDITO RETA | X92: =VLOOKUP(C92,Banorte!F:K,6,FALSE) -> #N/A | Z92: =X92-Y92 -> #N/A | AI92: 46170 | AO92: 614 | AP92: 46108 | AQ92: 46170 | AR92: RETA OP FIN
B93: 66 | C93: 615 | D93: USD | F93: MICHAEL DAVIS | G93: FOX | M93: RETA OP FIN | O93: SOLD | P93: 216900 | Q93: =P93*$U$3 -> 4012650 | R93: 87448 | T93: =P93-R93 -> 129452 | U93: =T93*U$3 -> 2394862 | W93: CREDITO RETA | X93: =VLOOKUP(C93,Banorte!F:K,6,FALSE) -> #N/A | Z93: =X93-Y93 -> #N/A | AI93: 46170 | AO93: 615 | AP93: 46108 | AQ93: 46170 | AR93: RETA OP FIN
B94: 67 | C94: 616 | D94: USD | F94: JAYME SALISBURY | G94: WILSON | M94: RETA OP FIN | O94: SOLD | P94: 216900 | Q94: =P94*$U$3 -> 4012650 | R94: 88450 | T94: =P94-R94 -> 128450 | U94: =T94*U$3 -> 2376325 | W94: CREDITO RETA | X94: =VLOOKUP(C94,Banorte!F:K,6,FALSE) -> #N/A | Z94: =X94-Y94 -> #N/A | AI94: 46170 | AO94: 616 | AP94: 46108 | AQ94: 46170 | AR94: RETA OP FIN
B95: 68 | C95: 617 | D95: USD | F95: KENT MARSHALL | G95: WHITE | M95: RETA OP FIN | O95: SOLD | P95: 216900 | Q95: =P95*$U$3 -> 4012650 | R95: 216400 | T95: =P95-R95 -> 500 | U95: =T95*U$3 -> 9250 | W95: CREDITO RETA | X95: =VLOOKUP(C95,Banorte!F:K,6,FALSE) -> #N/A | Z95: =X95-Y95 -> #N/A | AI95: 46170 | AO95: 617 | AP95: 46108 | AQ95: 46170 | AR95: RETA OP FIN | AS95: PAGADO
B96: 69 | C96: 701 | D96: USD | F96: STEVEN TODD | G96: WINGER | M96: RETA OP FIN | O96: SOLD | P96: 223900 | Q96: =P96*$U$3 -> 4142150 | R96: 111950 | T96: =P96-R96 -> 111950 | U96: =T96*U$3 -> 2071075 | W96: CREDITO RETA | X96: =VLOOKUP(C96,Banorte!F:K,6,FALSE) -> #N/A | Z96: =X96-Y96 -> #N/A | AI96: 46211 | AO96: 701 | AP96: 46183 | AQ96: 46211 | AR96: RETA OP FIN
B97: 70 | C97: 702 | D97: USD | F97: JAMES DONALD | G97: SLIPSAGER II | M97: RETA OP FIN | O97: SOLD | P97: 223900 | Q97: =P97*$U$3 -> 4142150 | R97: 97110 | T97: =P97-R97 -> 126790 | U97: =T97*U$3 -> 2345615 | W97: CREDITO RETA | X97: =VLOOKUP(C97,Banorte!F:K,6,FALSE) -> #N/A | Z97: =X97-Y97 -> #N/A | AI97: 46211 | AO97: 702 | AP97: 46183 | AQ97: 46211 | AR97: RETA OP FIN
B98: 71 | C98: 703 | D98: USD | F98: ALEXANDER | G98: GREGORY | M98: RETA OP FIN | O98: SOLD | P98: 223900 | Q98: =P98*$U$3 -> 4142150 | R98: 112050 | T98: =P98-R98 -> 111850 | U98: =T98*U$3 -> 2069225 | W98: CREDITO RETA | X98: =VLOOKUP(C98,Banorte!F:K,6,FALSE) -> #N/A | Z98: =X98-Y98 -> #N/A | AI98: 46211 | AO98: 703 | AP98: 46183 | AQ98: 46211 | AR98: RETA OP FIN
B99: 175 | C99: 704 | D99: MXN | F99: STEPHEN FOLCKER | G99: BOULAY | M99: GENERAL | O99: SOLD | Q99: 10700000 | S99: 8586216 | U99: =Q99-S99 -> 2113784 | X99: =VLOOKUP(C99,Banorte!F:K,6,FALSE) -> #N/A | Z99: =X99-Y99 -> #N/A | AI99: 46211 | AO99: 704 | AP99: 46183 | AQ99: 46211 | AR99: GENERAL
B100: 176 | C100: 705 | D100: MXN | F100: JAIME EDUARDO | G100: GARZA | H100: HERNANDEZ | M100: GENERAL | O100: SOLD | Q100: 9025000 | S100: 7220000 | U100: =Q100-S100 -> 1805000 | X100: =VLOOKUP(C100,Banorte!F:K,6,FALSE) -> #N/A | Z100: =X100-Y100 -> #N/A | AI100: 46211 | AO100: 705 | AP100: 46183 | AQ100: 46211 | AR100: GENERAL
B101: 72 | C101: 706 | D101: USD | F101: BENJIMAN DWAYNE | G101: READ | M101: RETA OP FIN | O101: SOLD | P101: 223900 | Q101: =P101*$U$3 -> 4142150 | R101: 89571 | T101: =P101-R101 -> 134329 | U101: =T101*U$3 -> 2485086.5 | W101: CREDITO RETA | X101: =VLOOKUP(C101,Banorte!F:K,6,FALSE) -> #N/A | Z101: =X101-Y101 -> #N/A | AI101: 46211 | AO101: 706 | AP101: 46183 | AQ101: 46211 | AR101: RETA OP FIN
...

Sheet Banorte
K2: =SUBTOTAL(9,K5:K195) -> 653920000
B3: CATALOGO DE CUENTAS | E3: INFORMACION ADICIONAL PARA REPORTES DE COBRANZA
B4: PROYECTO | C4: CUENTA | D4: SUBCUENTA | E4: EDIFICACION | F4: TIPO | G4: TIPO | H4: NIVEL | I4: VISTA | J4: M2 | K4: Valor liberacion
B5: YUCALPETEN E2 | C5: CLIENTES | D5: DEPTO B0301 | E5: BONANZA | F5: B-301 | G5: A2 | H5: 3 | I5: MAR | J5: 117.88 | K5: 2600000
B6: YUCALPETEN E2 | C6: CLIENTES | D6: DEPTO B0302 | E6: BONANZA | F6: B-302 | G6: A5 | H6: 3 | I6: MAR | J6: 117.88 | K6: 2600000
B7: YUCALPETEN E2 | C7: CLIENTES | D7: DEPTO B0303 | E7: BONANZA | F7: B-303 | G7: A3 | H7: 3 | I7: MARINA | J7: 117.88 | K7: 2600000
B8: YUCALPETEN E2 | C8: CLIENTES | D8: DEPTO B0306 | E8: BONANZA | F8: B-306 | G8: A3 | H8: 3 | I8: MARINA | J8: 117.88 | K8: 2600000
B9: YUCALPETEN E2 | C9: CLIENTES | D9: DEPTO B0307 | E9: BONANZA | F9: B-307 | G9: A5 | H9: 3 | I9: MARINA | J9: 117.88 | K9: 2600000
B10: YUCALPETEN E2 | C10: CLIENTES | D10: DEPTO B0308 | E10: BONANZA | F10: B-308 | G10: A2 | H10: 3 | I10: MAR | J10: 117.88 | K10: 2600000
B11: YUCALPETEN E2 | C11: CLIENTES | D11: DEPTO B0309 | E11: BONANZA | F11: B-309 | G11: A4 | H11: 3 | I11: MAR | J11: 117.88 | K11: 2600000
B12: YUCALPETEN E2 | C12: CLIENTES | D12: DEPTO B0310 | E12: BONANZA | F12: B-310 | G12: A2 | H12: 3 | I12: MAR | J12: 117.88 | K12: 2600000
B13: YUCALPETEN E2 | C13: CLIENTES | D13: DEPTO B0311 | E13: BONANZA | F13: B-311 | G13: A5 | H13: 3 | I13: MARINA | J13: 117.88 | K13: 2600000
B14: YUCALPETEN E2 | C14: CLIENTES | D14: DEPTO B0312 | E14: BONANZA | F14: B-312 | G14: A3 | H14: 3 | I14: MARINA | J14: 117.88 | K14: 2600000
B15: YUCALPETEN E2 | C15: CLIENTES | D15: DEPTO B0315 | E15: BONANZA | F15: B-315 | G15: A3 | H15: 3 | I15: MARINA | J15: 117.88 | K15: 2600000
B16: YUCALPETEN E2 | C16: CLIENTES | D16: DEPTO B0316 | E16: BONANZA | F16: B-316 | G16: A5 | H16: 3 | I16: MAR | J16: 117.88 | K16: 2600000
... B195: YUCALPETEN E2 | C195: CLIENTES | D195: DEPTO B1214 | E195: BONANZA | F195: BO-1214 | G195: D PH | H195: 12 | I195: MAR | J195: 303.63 | K195: 7160000

Sheet Vendidos x Ent Obra
B2: EDIFICIO | C2: UNIDADES | D2: SOLD | E2: AVAILABLE | F2: ENT OBRA A POSTV | G2: ENT A CTES | H2: CUST X ENTREG
B3: A | C3: =COUNTIF(Bonanza!$A$7:$A$197,'Vendidos x Ent Obra'!$B3) -> 0 | D3: =COUNTIFS(Bonanza!$A$7:$A$197,'Vendidos x Ent Obra'!$B3,Bonanza!$O$7:$O$197,'Vendidos x Ent Obra'!D$2) -> 0 | E3: =C3-D3 -> 0 | F3: =COUNTIFS(Bonanza!$A$7:$A$197,'Vendidos x Ent Obra'!$B3,Bonanza!#REF!,"ENTREGADO") -> #REF! | G3: =COUNTIFS(Bonanza!$A$7:$A$197,'Vendidos x Ent Obra'!$B3,Bonanza!$AE$7:$AE$197,"ENTREGADO") -> 0 | H3: =COUNTIFS(Bonanza!$A$7:$A$197,'Vendidos x Ent Obra'!$B3,Bonanza!$AE$7:$AE$197,"CUSTODIA") -> 0
B4: B | C4: =COUNTIF(Bonanza!$A$7:$A$197,'Vendidos x Ent Obra'!$B4) -> 0 | D4: =COUNTIFS(Bonanza!$A$7:$A$197,'Vendidos x Ent Obra'!$B4,Bonanza!$O$7:$O$197,'Vendidos x Ent Obra'!D$2) -> 0 | E4: =C4-D4 -> 0 | F4: =COUNTIFS(Bonanza!$A$7:$A$197,'Vendidos x Ent Obra'!$B4,Bonanza!#REF!,"ENTREGADO") -> #REF! | G4: =COUNTIFS(Bonanza!$A$7:$A$197,'Vendidos x Ent Obra'!$B4,Bonanza!$AE$7:$AE$197,"ENTREGADO") -> 0 | H4: =COUNTIFS(Bonanza!$A$7:$A$197,'Vendidos x Ent Obra'!$B4,Bonanza!$AE$7:$AE$197,"CUSTODIA") -> 0
B5: C | C5: =COUNTIF(Bonanza!$A$7:$A$197,'Vendidos x Ent Obra'!$B5) -> 0 | D5: =COUNTIFS(Bonanza!$A$7:$A$197,'Vendidos x Ent Obra'!$B5,Bonanza!$O$7:$O$197,'Vendidos x Ent Obra'!D$2) -> 0 | E5: =C5-D5 -> 0 | F5: =COUNTIFS(Bonanza!$A$7:$A$197,'Vendidos x Ent Obra'!$B5,Bonanza!#REF!,"ENTREGADO") -> #REF! | G5: =COUNTIFS(Bonanza!$A$7:$A$197,'Vendidos x Ent Obra'!$B5,Bonanza!$AE$7:$AE$197,"ENTREGADO") -> 0 | H5: =COUNTIFS(Bonanza!$A$7:$A$197,'Vendidos x Ent Obra'!$B5,Bonanza!$AE$7:$AE$197,"CUSTODIA") -> 0
B6: D | C6: =COUNTIF(Bonanza!$A$7:$A$197,'Vendidos x Ent Obra'!$B6) -> 0 | D6: =COUNTIFS(Bonanza!$A$7:$A$197,'Vendidos x Ent Obra'!$B6,Bonanza!$O$7:$O$197,'Vendidos x Ent Obra'!D$2) -> 0 | E6: =C6-D6 -> 0 | F6: =COUNTIFS(Bonanza!$A$7:$A$197,'Vendidos x Ent Obra'!$B6,Bonanza!#REF!,"ENTREGADO") -> #REF! | G6: =COUNTIFS(Bonanza!$A$7:$A$197,'Vendidos x Ent Obra'!$B6,Bonanza!$AE$7:$AE$197,"ENTREGADO") -> 0 | H6: =COUNTIFS(Bonanza!$A$7:$A$197,'Vendidos x Ent Obra'!$B6,Bonanza!$AE$7:$AE$197,"CUSTODIA") -> 0
B7: E | C7: =COUNTIF(Bonanza!$A$7:$A$197,'Vendidos x Ent Obra'!$B7) -> 0 | D7: =COUNTIFS(Bonanza!$A$7:$A$197,'Vendidos x Ent Obra'!$B7,Bonanza!$O$7:$O$197,'Vendidos x Ent Obra'!D$2) -> 0 | E7: =C7-D7 -> 0 | F7: =COUNTIFS(Bonanza!$A$7:$A$197,'Vendidos x Ent Obra'!$B7,Bonanza!#REF!,"ENTREGADO") -> #REF! | G7: =COUNTIFS(Bonanza!$A$7:$A$197,'Vendidos x Ent Obra'!$B7,Bonanza!$AE$7:$AE$197,"ENTREGADO") -> 0 | H7: =COUNTIFS(Bonanza!$A$7:$A$197,'Vendidos x Ent Obra'!$B7,Bonanza!$AE$7:$AE$197,"CUSTODIA") -> 0
B9: TOTALES | C9: =SUM(C3:C8) -> 0 | D9: =SUM(D3:D8) -> 0 | E9: =SUM(E3:E8) -> 0 | F9: =SUM(F3:F8) -> #REF! | G9: =SUM(G3:G8) -> 0 | H9: =SUM(H3:H8) -> 0
F10: =IF(F9=SUM(G9:H9),"OK","ERROR") -> #REF!

Sheet CANCELACIONES
A1: DEPTO | B1: TYPE | C1: NOMBRE (S) | D1: APELLIDO 1 | E1: APELLIDO 2 | F1: ALIAS / RAZON SOCIAL | G1: @mail | H1: LADA | I1: Telefono | J1: TIPO CLIENTE | K1: TIPO CONTRATO | L1: STATUS SISTEMA | M1: Monto Venta | N1: PAGADO | O1: SALDO | P1: SALDO MN | Q1: FECHA COBRO SALDO | R1: FORMA PAGO | S1: VALOR LIBERACION | T1: PAGADO LIBERACION | U1: X PAGAR | V1: FECHA LIBERACIÓN | W1: ESCRITURACION | X1: FECHA ESCRITURACION | Y1: NOTARIA | Z1: STATUS SOS | AA1: FECHA SEGÚN CONTRATO | AB1: FECHA SOS | AC1: FECHA ENTREGA OBRA | AD1: FECHA ENTREGA CLIENTE | AE1: COMENTARIOS | AF1: TICKET
